oddball/__init__.py
oddball/config.py
oddball/enums.py
oddball/data/__init__.py
oddball/data/loader.py
oddball/data/registry.py
oddball/data/setup.py
oddball/generator/__init__.py
oddball/generator/base.py
oddball/generator/batch.py
oddball/generator/online.py
oddball-1.4.0.dist-info/METADATA
oddball-1.4.0.dist-info/WHEEL
oddball-1.4.0.dist-info/licenses/LICENSE
oddball-1.4.0.dist-info/RECORD
