Metadata-Version: 2.4
Name: oddball
Version: 1.4.0
Summary: Anomaly Detection Dataset Collection
Project-URL: Homepage, https://github.com/OliverHennhoefer/oddball
Project-URL: Repository, https://github.com/OliverHennhoefer/oddball
Project-URL: Issues, https://github.com/OliverHennhoefer/oddball/issues
Author: Oddball Maintainers
License: MIT License
License-File: LICENSE
Keywords: adbench,anomaly-detection,datasets,npz
Classifier: Intended Audience :: Science/Research
Classifier: License :: OSI Approved :: MIT License
Classifier: Operating System :: OS Independent
Classifier: Programming Language :: Python :: 3
Classifier: Programming Language :: Python :: 3.12
Requires-Python: >=3.12
Requires-Dist: numpy>=1.23
Requires-Dist: pandas>=2.2
Requires-Dist: scikit-learn>=1.4
Provides-Extra: tests
Requires-Dist: pytest>=7.4; extra == 'tests'
